PackageDeployTester/Module.py
PackageDeployTester/__init__.py
packagedeploytester-0.1.0.dist-info/METADATA
packagedeploytester-0.1.0.dist-info/WHEEL
packagedeploytester-0.1.0.dist-info/top_level.txt
packagedeploytester-0.1.0.dist-info/RECORD
