Metadata-Version: 2.4
Name: PackageDeployTester
Version: 0.1.0
Summary: PyPi에 my Package Upload 해보기
Home-page: https://github.com/Dev9er/PackageDeployTester
Author: Dev9er
Author-email: Dev9er@gmail.com
License: MIT
Classifier: Development Status :: 1 - Planning
Classifier: License :: OSI Approved :: MIT License
Classifier: Programming Language :: Python :: 3
Classifier: Operating System :: OS Independent
Requires-Python: >=3.6
Dynamic: author
Dynamic: author-email
Dynamic: classifier
Dynamic: description
Dynamic: description-content-type
Dynamic: home-page
Dynamic: license
Dynamic: requires-python
Dynamic: summary
